mcc/ChatBot.py
mcc/__init__.py
mcc/command.py
mcc/mcc.py
mcc/commands/AuthenticateCommand.py
mcc/commands/ChangeSessionIdCommand.py
mcc/commands/ChangeSlotCommand.py
mcc/commands/ClearInventoriesCommand.py
mcc/commands/ClientIsMovingCommand.py
mcc/commands/CloseInventoryCommand.py
mcc/commands/CreativeDeleteCommand.py
mcc/commands/CreativeGiveCommand.py
mcc/commands/DigBlockCommand.py
mcc/commands/DisconnectAndExitCommand.py
mcc/commands/GetCurrentLocationCommand.py
mcc/commands/GetCurrentSlotCommand.py
mcc/commands/GetEntitiesCommand.py
mcc/commands/GetEntityHandlingEnabledCommand.py
mcc/commands/GetGamemodeCommand.py
mcc/commands/GetInventoriesCommand.py
mcc/commands/GetInventoryEnabledCommand.py
mcc/commands/GetMaxChatMessageLengthCommand.py
mcc/commands/GetOnlinePlayersCommand.py
mcc/commands/GetOnlinePlayersWithUUIDCommand.py
mcc/commands/GetPitchCommand.py
mcc/commands/GetPlayerInventoryCommand.py
mcc/commands/GetPlayersLatencyCommand.py
mcc/commands/GetServerHostCommand.py
mcc/commands/GetServerPortCommand.py
mcc/commands/GetServerTPSCommand.py
mcc/commands/GetTerrainEnabledCommand.py
mcc/commands/GetTimestampCommand.py
mcc/commands/GetUserUUIDCommand.py
mcc/commands/GetUsernameCommand.py
mcc/commands/GetWorldCommand.py
mcc/commands/GetYawCommand.py
mcc/commands/InteractEntityCommand.py
mcc/commands/LogDebugToConsoleCommand.py
mcc/commands/LogDebugToConsoleTranslatedCommand.py
mcc/commands/LogToConsoleCommand.py
mcc/commands/LogToConsoleTranslatedCommand.py
mcc/commands/LookAtLocationCommand.py
mcc/commands/MoveToLocationCommand.py
mcc/commands/ReconnectToTheServerCommand.py
mcc/commands/RespawnCommand.py
mcc/commands/RunScriptCommand.py
mcc/commands/SelectTradeCommand.py
mcc/commands/SendAnimationCommand.py
mcc/commands/SendEntityActionCommand.py
mcc/commands/SendPlaceBlockCommand.py
mcc/commands/SetSlotCommand.py
mcc/commands/SetTerrainEnabledCommand.py
mcc/commands/SneakCommand.py
mcc/commands/UpdateCommandBlockCommand.py
mcc/commands/UpdateSignCommand.py
mcc.py-0.0.23.dist-info/LICENSE.md
mcc.py-0.0.23.dist-info/METADATA
mcc.py-0.0.23.dist-info/WHEEL
mcc.py-0.0.23.dist-info/top_level.txt
mcc.py-0.0.23.dist-info/RECORD
