Metadata-Version: 2.1
Name: mcc.py
Version: 0.0.23
Summary: Python bindings for controlling the Minecraft Console Client Websocket bot
Author-email: zorua162 <zorua162@gmail.com>
Project-URL: Homepage, https://github.com/Zorua162/mcc.py
Project-URL: Issues, https://github.com/Zorua162/mcc.py/issues
Requires-Python: >=3.8
License-File: LICENSE.md
Requires-Dist: websockets
